django_rest_offlinesync-0.5.2.dist-info/DESCRIPTION.rst
django_rest_offlinesync-0.5.2.dist-info/METADATA
django_rest_offlinesync-0.5.2.dist-info/RECORD
django_rest_offlinesync-0.5.2.dist-info/WHEEL
django_rest_offlinesync-0.5.2.dist-info/metadata.json
django_rest_offlinesync-0.5.2.dist-info/top_level.txt
rest_offlinesync/__init__.py
rest_offlinesync/delete.py
rest_offlinesync/limit.py
rest_offlinesync/mixin.py
rest_offlinesync/models.py
rest_offlinesync/nest.py
rest_offlinesync/sync.py
rest_offlinesync/management/__init__.py
rest_offlinesync/management/commands/__init__.py
rest_offlinesync/management/commands/cleardeleted.py
