Metadata-Version: 2.0
Name: django-rest-offlinesync
Version: 0.5.2
Summary: Offline Data Synchronization for Django REST Framework
Home-page: https://github.com/vsemionov/django-rest-offlinesync
Author: Victor Semionov
Author-email: vsemionov@gmail.com
License: MIT
Keywords: offline data synchronization django rest python
Platform: UNKNOWN
Classifier: Development Status :: 4 - Beta
Classifier: Environment :: Web Environment
Classifier: Framework :: Django
Classifier: Intended Audience :: Developers
Classifier: License :: OSI Approved :: MIT License
Classifier: Operating System :: OS Independent
Classifier: Programming Language :: Python :: 3
Classifier: Topic :: Internet :: WWW/HTTP
Classifier: Topic :: Software Development :: Libraries
Requires-Dist: Django
Requires-Dist: djangorestframework
